dunder_xml_reader/__init__.py
dunder_xml_reader/safe_reference.py
dunder_xml_reader/xml_node.py
dunder_xml_reader/xml_node_list.py
dunder_xml_reader-0.1.1.dist-info/METADATA
dunder_xml_reader-0.1.1.dist-info/WHEEL
dunder_xml_reader-0.1.1.dist-info/RECORD
